LICENSE
README.md
setup.cfg
setup.py
cognifly/__init__.py
cognifly/__main__.py
cognifly.egg-info/PKG-INFO
cognifly.egg-info/SOURCES.txt
cognifly.egg-info/dependency_links.txt
cognifly.egg-info/requires.txt
cognifly.egg-info/top_level.txt
cognifly/cognifly_controller/__init__.py
cognifly/cognifly_controller/cognifly_controller.py
cognifly/cognifly_controller/dummy_controller.py
cognifly/cognifly_remote/__init__.py
cognifly/cognifly_remote/cognifly_remote.py
cognifly/cognifly_remote/sprites/gamepad_off.png
cognifly/cognifly_remote/sprites/gamepad_on.png
cognifly/utils/__init__.py
cognifly/utils/filters.py
cognifly/utils/functions.py
cognifly/utils/ip_tools.py
cognifly/utils/joysticks.py
cognifly/utils/pid.py
cognifly/utils/tcp_video_interface.py
cognifly/utils/udp_interface.py
scripts/cognifly-controller