Metadata-Version: 2.1
Name: cognifly
Version: 0.3.0
Summary: Control the CogniFly open-source drone from python
Home-page: https://github.com/thecognifly/cognifly-python
Download-URL: https://github.com/thecognifly/cognifly-python/archive/refs/tags/v0.3.0.tar.gz
Author: Yann Bouteiller
License: MIT
Keywords: cognifly,drone,remote,control
Platform: UNKNOWN
Classifier: Development Status :: 4 - Beta
Classifier: Intended Audience :: Developers
Classifier: Intended Audience :: Education
Classifier: Intended Audience :: Information Technology
Classifier: Intended Audience :: Science/Research
Classifier: License :: OSI Approved :: MIT License
Classifier: Operating System :: Microsoft :: Windows
Classifier: Operating System :: POSIX :: Linux
Classifier: Programming Language :: Python
Classifier: Framework :: Robot Framework :: Library
Classifier: Topic :: Education
Classifier: Topic :: Scientific/Engineering :: Artificial Intelligence
License-File: LICENSE
